MANIFEST.in
README.md
setup.py
central_message/__init__.py
central_message/admin.py
central_message/models.py
central_message/migrations/0001_initial.py
central_message/migrations/__init__.py
central_message/south_migrations/0001_initial.py
central_message/south_migrations/__init__.py
django_central_message.egg-info/PKG-INFO
django_central_message.egg-info/SOURCES.txt
django_central_message.egg-info/dependency_links.txt
django_central_message.egg-info/not-zip-safe
django_central_message.egg-info/requires.txt
django_central_message.egg-info/top_level.txt
requirements/common.txt
requirements/development.txt
requirements/production.txt
requirements/testing.txt