Metadata-Version: 1.0
Name: django-central-message
Version: 0.1.3
Summary: Wrapper for extends-messages to send to multiple users (all for now) from the admin page..
Home-page: UNKNOWN
Author: Nimbis Services, Inc.
Author-email: info@nimbisservices.com
License: BSD
Platform: UNKNOWN
